mock_data_forge/__init__.py
mock_data_forge/__main__.py
mock_data_forge/generator.py
mock_data_forge-0.1.1.dist-info/licenses/LICENSE
mock_data_forge-0.1.1.dist-info/METADATA
mock_data_forge-0.1.1.dist-info/WHEEL
mock_data_forge-0.1.1.dist-info/entry_points.txt
mock_data_forge-0.1.1.dist-info/top_level.txt
mock_data_forge-0.1.1.dist-info/RECORD
