Metadata-Version: 2.4
Name: mock-data-forge
Version: 0.1.1
Summary: A CLI tool to generate mock JSON data from schemas, with optional API posting and file saving.
Author-email: Manav Sharma <manavs19102006@gmail.com>
License: MIT
Project-URL: Homepage, https://github.com/HattoriMan/Mock-Data-Forge-CLI
Project-URL: Repository, https://github.com/HattoriMan/Mock-Data-Forge-CLI
Project-URL: Issues, https://github.com/HattoriMan/Mock-Data-Forge-CLI/issues
Keywords: mock,json,data,cli,faker,generator
Classifier: Programming Language :: Python :: 3
Classifier: License :: OSI Approved :: MIT License
Classifier: Operating System :: OS Independent
Requires-Python: >=3.7
License-File: LICENSE
Requires-Dist: faker>=19.0
Requires-Dist: rstr>=2.0
Requires-Dist: requests>=2.31.0
Dynamic: license-file
